{
    "metadata": {
      "country": "Egypt",
      "currency": "EGP",
      "lastUpdated": "2026-01-01",
      "sourceType": "sample-structured-dataset"
    },
    "cars": [
      {
        "id": 1,
        "brand": "Toyota",
        "model": "Corolla",
        "year": 2024,
        "bodyType": "Sedan",
        "fuelType": "Petrol",
        "transmission": "Automatic",
        "engineCc": 1600,
        "horsePower": 120,
        "price": 1250000,
        "availability": "Available",
        "origin": "Imported"
      },
      {
        "id": 2,
        "brand": "Nissan",
        "model": "Sunny",
        "year": 2024,
        "bodyType": "Sedan",
        "fuelType": "Petrol",
        "transmission": "Automatic",
        "engineCc": 1500,
        "horsePower": 108,
        "price": 850000,
        "availability": "Available",
        "origin": "Local Assembly"
      },
      {
        "id": 3,
        "brand": "Hyundai",
        "model": "Elantra CN7",
        "year": 2025,
        "bodyType": "Sedan",
        "fuelType": "Petrol",
        "transmission": "Automatic",
        "engineCc": 1600,
        "horsePower": 127,
        "price": 1350000,
        "availability": "Limited",
        "origin": "Imported"
      },
      {
        "id": 4,
        "brand": "Kia",
        "model": "Sportage",
        "year": 2025,
        "bodyType": "SUV",
        "fuelType": "Petrol",
        "transmission": "Automatic",
        "engineCc": 1600,
        "horsePower": 180,
        "price": 2100000,
        "availability": "Available",
        "origin": "Imported"
      },
      {
        "id": 5,
        "brand": "MG",
        "model": "ZS",
        "year": 2024,
        "bodyType": "SUV",
        "fuelType": "Petrol",
        "transmission": "Automatic",
        "engineCc": 1500,
        "horsePower": 119,
        "price": 1150000,
        "availability": "Available",
        "origin": "Imported"
      },
      {
        "id": 6,
        "brand": "Chevrolet",
        "model": "Optra",
        "year": 2024,
        "bodyType": "Sedan",
        "fuelType": "Petrol",
        "transmission": "Automatic",
        "engineCc": 1500,
        "horsePower": 110,
        "price": 780000,
        "availability": "Available",
        "origin": "Local Assembly"
      },
      {
        "id": 7,
        "brand": "Chery",
        "model": "Tiggo 7 Pro",
        "year": 2025,
        "bodyType": "SUV",
        "fuelType": "Petrol",
        "transmission": "Automatic",
        "engineCc": 1500,
        "horsePower": 145,
        "price": 1650000,
        "availability": "Limited",
        "origin": "Local Assembly"
      },
      {
        "id": 8,
        "brand": "BYD",
        "model": "Dolphin",
        "year": 2025,
        "bodyType": "Hatchback",
        "fuelType": "Electric",
        "transmission": "Automatic",
        "engineCc": 0,
        "horsePower": 95,
        "price": 1700000,
        "availability": "Preorder",
        "origin": "Imported"
      },
      {
        "id": 9,
        "brand": "Peugeot",
        "model": "3008",
        "year": 2024,
        "bodyType": "SUV",
        "fuelType": "Petrol",
        "transmission": "Automatic",
        "engineCc": 1600,
        "horsePower": 165,
        "price": 2200000,
        "availability": "Available",
        "origin": "Imported"
      },
      {
        "id": 10,
        "brand": "Skoda",
        "model": "Octavia A8",
        "year": 2025,
        "bodyType": "Sedan",
        "fuelType": "Petrol",
        "transmission": "Automatic",
        "engineCc": 1400,
        "horsePower": 150,
        "price": 1950000,
        "availability": "Limited",
        "origin": "Imported"
      }
    ]
  }
  